alibabacloud_cloudauth_intl20220809/__init__.py
alibabacloud_cloudauth_intl20220809/client.py
alibabacloud_cloudauth_intl20220809/models/__init__.py
alibabacloud_cloudauth_intl20220809/models/_add_face_record_advance_request.py
alibabacloud_cloudauth_intl20220809/models/_add_face_record_request.py
alibabacloud_cloudauth_intl20220809/models/_add_face_record_response.py
alibabacloud_cloudauth_intl20220809/models/_add_face_record_response_body.py
alibabacloud_cloudauth_intl20220809/models/_address_compare_intl_request.py
alibabacloud_cloudauth_intl20220809/models/_address_compare_intl_response.py
alibabacloud_cloudauth_intl20220809/models/_address_compare_intl_response_body.py
alibabacloud_cloudauth_intl20220809/models/_address_verify_intl_request.py
alibabacloud_cloudauth_intl20220809/models/_address_verify_intl_response.py
alibabacloud_cloudauth_intl20220809/models/_address_verify_intl_response_body.py
alibabacloud_cloudauth_intl20220809/models/_address_verify_v2intl_request.py
alibabacloud_cloudauth_intl20220809/models/_address_verify_v2intl_response.py
alibabacloud_cloudauth_intl20220809/models/_address_verify_v2intl_response_body.py
alibabacloud_cloudauth_intl20220809/models/_bank_meta_verify_intl_request.py
alibabacloud_cloudauth_intl20220809/models/_bank_meta_verify_intl_response.py
alibabacloud_cloudauth_intl20220809/models/_bank_meta_verify_intl_response_body.py
alibabacloud_cloudauth_intl20220809/models/_card_ocr_request.py
alibabacloud_cloudauth_intl20220809/models/_card_ocr_response.py
alibabacloud_cloudauth_intl20220809/models/_card_ocr_response_body.py
alibabacloud_cloudauth_intl20220809/models/_check_result_request.py
alibabacloud_cloudauth_intl20220809/models/_check_result_response.py
alibabacloud_cloudauth_intl20220809/models/_check_result_response_body.py
alibabacloud_cloudauth_intl20220809/models/_check_verify_log_request.py
alibabacloud_cloudauth_intl20220809/models/_check_verify_log_response.py
alibabacloud_cloudauth_intl20220809-3.17.1.dist-info/LICENSE
alibabacloud_cloudauth_intl20220809-3.17.1.dist-info/METADATA
alibabacloud_cloudauth_intl20220809-3.17.1.dist-info/WHEEL
alibabacloud_cloudauth_intl20220809-3.17.1.dist-info/top_level.txt
alibabacloud_cloudauth_intl20220809-3.17.1.dist-info/RECORD
